dnevniklib/__init__.py
dnevniklib/errors.py
dnevniklib/homeworks.py
dnevniklib/marks.py
dnevniklib/school.py
dnevniklib/user.py
dnevniklib-0.5.dist-info/METADATA
dnevniklib-0.5.dist-info/WHEEL
dnevniklib-0.5.dist-info/top_level.txt
dnevniklib-0.5.dist-info/RECORD
