Metadata-Version: 2.1
Name: dnevniklib
Version: 0.5
Summary: lib for automatization work with dnevnik mos
Home-page: https://github.com/dirtyhornet277/dnevniklib
Author: Ivan Kriventsev
Author-email: dirtyhornet277@outlook.com
Requires-Python: >=3.6
